SubtitleTranslator/SubtitleTranslator.py
SubtitleTranslator/Translator.py
SubtitleTranslator/__init__.py
SubtitleTranslator/constants.py
SubtitleTranslator/test.py
subtrans-1.0.3.dist-info/LICENSE
subtrans-1.0.3.dist-info/METADATA
subtrans-1.0.3.dist-info/WHEEL
subtrans-1.0.3.dist-info/entry_points.txt
subtrans-1.0.3.dist-info/top_level.txt
subtrans-1.0.3.dist-info/RECORD
